ai_z-0.3.1.data/scripts/ai-z
aiz/__init__.py
aiz/aiz.py
aiz/cpu.py
aiz/gpu_amd.py
aiz/gpu_nvidia.py
aiz/hwinfo.py
ai_z-0.3.1.dist-info/LICENSE
ai_z-0.3.1.dist-info/METADATA
ai_z-0.3.1.dist-info/WHEEL
ai_z-0.3.1.dist-info/top_level.txt
ai_z-0.3.1.dist-info/RECORD
