Metadata-Version: 2.1
Name: ai-z
Version: 0.3.1
Summary: GPU usage graph in the terminal for AMD and NVIDIA GPUs
Home-page: https://www.ai-z.org
Author: Mathieu Poliquin
Author-email: mathieu.poliquin@gmail.com
License: MIT
Platform: UNKNOWN
Classifier: Programming Language :: Python :: 3
Classifier: License :: OSI Approved :: MIT License
Classifier: Operating System :: OS Independent
Requires-Python: >=3.6
Requires-Dist: py3nvml
Requires-Dist: numpy
Requires-Dist: psutil
Requires-Dist: py-cpuinfo
Requires-Dist: sparklines
